multimd/LICENSE.txt
multimd/README.md
multimd/__init__.py
multimd/__main__.py
multimd/build.py
multimd/cli.py
multimd/toc.py
multimd-0.3.2b0.dist-info/METADATA
multimd-0.3.2b0.dist-info/WHEEL
multimd-0.3.2b0.dist-info/entry_points.txt
multimd-0.3.2b0.dist-info/RECORD
