Metadata-Version: 2.1
Name: multimd
Version: 0.3.2b0
Summary: This project makes it possible to write separated pieces of `MD` files that will be merged to produce one single final `MD` file.
Home-page: https://github.com/bc-tools/for-dev/tree/main/multimd
License: GNU License Version 3
Author: Christophe BAL
Maintainer: Christophe BAL
Requires-Python: >=3.8,<4.0
Classifier: License :: Other/Proprietary License
Classifier: Programming Language :: Python :: 3
Classifier: Programming Language :: Python :: 3.8
Classifier: Programming Language :: Python :: 3.9
Classifier: Programming Language :: Python :: 3.10
Classifier: Programming Language :: Python :: 3.11
Requires-Dist: natsort (>=8.2,<9.0)
Requires-Dist: rich (>=13.3.5,<14.0.0)
Requires-Dist: typer (>=0.9,<0.10)
Project-URL: Repository, https://github.com/bc-tools/for-dev/tree/main/multimd
